Samuel_Lin-0.1.0.dist-info/.ipynb_checkpoints/dependency_links-checkpoint.txt
imdb/__init__.py
imdb/__main__.py
imdb/api.py
imdb/imdb.py
Samuel_Lin-0.1.0.dist-info/LICENSE
Samuel_Lin-0.1.0.dist-info/METADATA
Samuel_Lin-0.1.0.dist-info/WHEEL
Samuel_Lin-0.1.0.dist-info/top_level.txt
Samuel_Lin-0.1.0.dist-info/RECORD
